{
  "resourceSpans": [
    {
      "resource": {
        "attributes": [
          {
            "key": "service.name",
            "value": {
              "stringValue": "WinFormsApp"
            }
          }
        ]
      },
      "scopeSpans": [
        {
          "scope": {
            "name": "WinFormsAppTracer"
          },
          "spans": [
            {
              "traceId": "8819a40ce1bc1c9cf2f702864e724514",
              "spanId": "df8b7932774d90df",
              "name": "simulate_error",
              "startTimeUnixNano": 8548648471521758952,
              "endTimeUnixNano": 8548648471630635052,
              "kind": "SPAN_KIND_INTERNAL",
              "status": {
                "code": "STATUS_CODE_ERROR"
              },
              "attributes": [],
              "events": [],
              "links": []
            }
          ]
        }
      ]
    }
  ]
}